async_bus/__init__.py
async_bus/event_bus.py
tests/__init__.py
tests/test_event_bus.py
py_async_bus-0.0.1.dist-info/LICENSE
py_async_bus-0.0.1.dist-info/METADATA
py_async_bus-0.0.1.dist-info/WHEEL
py_async_bus-0.0.1.dist-info/top_level.txt
py_async_bus-0.0.1.dist-info/RECORD
