Metadata-Version: 2.1
Name: py-async-bus
Version: 0.0.1
Summary: A simple async event bus in Python
Home-page: https://github.com/nicolaszein/py-async-bus
Author: Nícolas Zein
Author-email: niczein@gmail.com
License: UNKNOWN
Platform: UNKNOWN
Classifier: Programming Language :: Python :: 3.7
Classifier: License :: OSI Approved :: MIT License
Classifier: Operating System :: OS Independent
Requires-Python: >=3.7
